MANIFEST.in
README.rst
bootstrap.py
buildout.cfg
setup.cfg
setup.py
Products/__init__.py
Products.ATGoogleVideo.egg-info/PKG-INFO
Products.ATGoogleVideo.egg-info/SOURCES.txt
Products.ATGoogleVideo.egg-info/dependency_links.txt
Products.ATGoogleVideo.egg-info/entry_points.txt
Products.ATGoogleVideo.egg-info/namespace_packages.txt
Products.ATGoogleVideo.egg-info/not-zip-safe
Products.ATGoogleVideo.egg-info/requires.txt
Products.ATGoogleVideo.egg-info/top_level.txt
Products/ATGoogleVideo/__init__.py
Products/ATGoogleVideo/config.py
Products/ATGoogleVideo/configure.zcml
Products/ATGoogleVideo/interfaces.py
Products/ATGoogleVideo/setuphandlers.py
Products/ATGoogleVideo/testing.py
Products/ATGoogleVideo/validator.py
Products/ATGoogleVideo/Extensions/Install.py
Products/ATGoogleVideo/Extensions/__init__.py
Products/ATGoogleVideo/content/__init__.py
Products/ATGoogleVideo/content/googlevideo.py
Products/ATGoogleVideo/i18n/atgooglevideo-el.po
Products/ATGoogleVideo/i18n/atgooglevideo-es.po
Products/ATGoogleVideo/i18n/atgooglevideo-eu.po
Products/ATGoogleVideo/i18n/atgooglevideo-it.po
Products/ATGoogleVideo/i18n/atgooglevideo-plone-el.po
Products/ATGoogleVideo/i18n/atgooglevideo-plone-es.po
Products/ATGoogleVideo/i18n/atgooglevideo-plone-eu.po
Products/ATGoogleVideo/i18n/atgooglevideo-plone-it.po
Products/ATGoogleVideo/i18n/atgooglevideo-plone-pt-br.po
Products/ATGoogleVideo/i18n/atgooglevideo-plone.pot
Products/ATGoogleVideo/i18n/atgooglevideo-pt-br.po
Products/ATGoogleVideo/i18n/atgooglevideo.pot
Products/ATGoogleVideo/profiles/default/atgooglevideo_various.txt
Products/ATGoogleVideo/profiles/default/factorytool.xml
Products/ATGoogleVideo/profiles/default/import_steps.xml
Products/ATGoogleVideo/profiles/default/jsregistry.xml
Products/ATGoogleVideo/profiles/default/metadata.xml
Products/ATGoogleVideo/profiles/default/propertiestool.xml
Products/ATGoogleVideo/profiles/default/rolemap.xml
Products/ATGoogleVideo/profiles/default/skins.xml
Products/ATGoogleVideo/profiles/default/types.xml
Products/ATGoogleVideo/profiles/default/types/Google_Video.xml
Products/ATGoogleVideo/skins/atgooglevideo_images/flash.gif
Products/ATGoogleVideo/skins/atgooglevideo_images/googlevideo.png
Products/ATGoogleVideo/skins/atgooglevideo_images/googlevideo_icon.gif
Products/ATGoogleVideo/skins/atgooglevideo_templates/getLatestGoogleVideo.py
