Metadata-Version: 1.0
Name: Products.ATGoogleVideo
Version: 0.9.1
Summary: Use YouTube and Google Video on a Plone Site.
Home-page: https://svn.plone.org/svn/collective/Products.ATGoogleVideo
Author: Héctor Velarde
Author-email: hector.velarde@gmail.com
License: GPL
Keywords: plone youtube video google
Platform: UNKNOWN
Classifier: Development Status :: 6 - Mature
Classifier: Environment :: Web Environment
Classifier: Framework :: Plone
Classifier: Framework :: Plone :: 3.2
Classifier: Framework :: Plone :: 3.3
Classifier: Framework :: Plone :: 4.0
Classifier: Framework :: Plone :: 4.1
Classifier: Intended Audience :: System Administrators
Classifier: License :: OSI Approved :: GNU General Public License (GPL)
Classifier: Operating System :: OS Independent
Classifier: Programming Language :: JavaScript
Classifier: Programming Language :: Python
Classifier: Programming Language :: Python :: 2.6
Classifier: Topic :: Software Development :: Libraries :: Python Modules
